slll/__init__.py
slll/csll.py
slll/slll.py
single_linked_list-0.0.3.dist-info/METADATA
single_linked_list-0.0.3.dist-info/WHEEL
single_linked_list-0.0.3.dist-info/top_level.txt
single_linked_list-0.0.3.dist-info/RECORD
