Metadata-Version: 2.1
Name: single-linked-list
Version: 0.0.3
Summary: A Python implementation of a singly linked list
Home-page: https://github.com/ahmedkmadani/single-linked-list
Author: Ahmed K. Madani
Author-email: ahmedk.madani@outlook.com
License: UNKNOWN
Platform: UNKNOWN
Classifier: Development Status :: 3 - Alpha
Classifier: Intended Audience :: Developers
Classifier: License :: OSI Approved :: MIT License
Classifier: Programming Language :: Python :: 3
Classifier: Programming Language :: Python :: 3.6
Classifier: Programming Language :: Python :: 3.7
Classifier: Programming Language :: Python :: 3.8
Classifier: Programming Language :: Python :: 3.9
